django_ultra_rbac/__init__.py
django_ultra_rbac/admin.py
django_ultra_rbac/decorators.py
django_ultra_rbac/middleware.py
django_ultra_rbac/models.py
django_ultra_rbac-0.1.1.dist-info/LICENSE
django_ultra_rbac-0.1.1.dist-info/METADATA
django_ultra_rbac-0.1.1.dist-info/WHEEL
django_ultra_rbac-0.1.1.dist-info/top_level.txt
django_ultra_rbac-0.1.1.dist-info/RECORD
