Metadata-Version: 2.1
Name: django-ultra-rbac
Version: 0.1.1
Summary: A flexible RBAC system for Django
Home-page: https://github.com/seamuddin/Django-Ultra-RBAC/
Author: Seam Uddin
Author-email: seamuddin.me@gmail.com
License: MIT
Project-URL: Bug Tracker, https://github.com/yourusername/django-ultra-rbac/issues
Classifier: Environment :: Web Environment
Classifier: Framework :: Django
Classifier: Intended Audience :: Developers
Classifier: License :: OSI Approved :: MIT License
Classifier: Operating System :: OS Independent
Classifier: Programming Language :: Python
Classifier: Programming Language :: Python :: 3
Classifier: Topic :: Internet :: WWW/HTTP
Classifier: Topic :: Security
Requires-Python: >=3.8
License-File: LICENSE
Requires-Dist: Django>=3.2
